cinnamon_generic/__init__.py
cinnamon_generic/api/__init__.py
cinnamon_generic/api/commands.py
cinnamon_generic/components/__init__.py
cinnamon_generic/components/calibrator.py
cinnamon_generic/components/callback.py
cinnamon_generic/components/command_runner.py
cinnamon_generic/components/data_loader.py
cinnamon_generic/components/data_splitter.py
cinnamon_generic/components/file_manager.py
cinnamon_generic/components/helper.py
cinnamon_generic/components/metrics.py
cinnamon_generic/components/model.py
cinnamon_generic/components/pipeline.py
cinnamon_generic/components/processor.py
cinnamon_generic/components/routine.py
cinnamon_generic/components/routine_processor.py
cinnamon_generic/configurations/__init__.py
cinnamon_generic/configurations/calibrator.py
cinnamon_generic/configurations/command_runner.py
cinnamon_generic/configurations/data_loader.py
cinnamon_generic/configurations/data_splitter.py
cinnamon_generic/configurations/file_manager.py
cinnamon_generic/configurations/helper.py
cinnamon_generic/configurations/metrics.py
cinnamon_generic/configurations/model.py
cinnamon_generic/configurations/pipeline.py
cinnamon_generic/configurations/routine.py
cinnamon_generic/configurations/routine_processor.py
cinnamon_generic/nlp/__init__.py
cinnamon_generic-0.1.dist-info/LICENSE
cinnamon_generic-0.1.dist-info/METADATA
cinnamon_generic-0.1.dist-info/WHEEL
cinnamon_generic-0.1.dist-info/top_level.txt
cinnamon_generic-0.1.dist-info/RECORD
