Metadata-Version: 2.1
Name: cinnamon-generic
Version: 0.1
Summary: [Generic Package] A simple high-level framework for research
Home-page: https://github.com/federicoruggeri/cinnamon_generic
Author: Federico Ruggeri
Author-email: federico.ruggeri6@unibo.it
License: MIT
Project-URL: Bug Tracker, https://github.com/federicoruggeri/cinnamon_generic/issues
Platform: UNKNOWN
Classifier: Programming Language :: Python :: 3
Classifier: Operating System :: OS Independent
Requires-Python: >=3.6
Requires-Dist: hyperopt (==0.2.7)
Requires-Dist: setuptools (>=47.1.0)
Requires-Dist: pytest (>=7.3.1)
Requires-Dist: tqdm (>=4.64.0)
Requires-Dist: gensim (~=4.2.0)
Requires-Dist: numpy (>=1.21.6)
Requires-Dist: pandas (>=1.3.5)
Requires-Dist: scikit-learn (>=1.0.2)
